<?xml version="1.0" encoding="utf-8"?><toc><breadcrumbs><li><a href="29411023-0052-089d-f65f-b19dc7aea29c.htm">Docs</a></li><li><a href="29411023-0052-089d-f65f-b19dc7aea29c.htm">Nur<wbr />Api<wbr />Dot<wbr />Net</a></li><li><a href="0e0f858a-0a91-eaf5-b12d-21e867cf0f53.htm">Nur<wbr />Api.<wbr />Accessory<wbr />Sensor<wbr />Config</a></li></breadcrumbs><tocItems><li><a id="e469ab08-fd81-4277-6777-d071aeff4035" href="e469ab08-fd81-4277-6777-d071aeff4035.htm">Constructor</a></li><li><a id="a3cf7b91-3e46-ae6c-e0b9-b5429c2e3a75" class="has-submenu" href="a3cf7b91-3e46-ae6c-e0b9-b5429c2e3a75.htm"><span data-tocFile="../toc/IDB0JB0A.xml" class="icon toggle" onclick="ToggleExpandCollapse(this); return false;"><i class="fa fa-angle-right"> </i></span>Methods</a><ul class="toc-menu is-hidden"> </ul></li><li><a id="3e3fc3d8-aac3-c5c2-6d0e-099f9d506b6a" class="has-submenu" href="3e3fc3d8-aac3-c5c2-6d0e-099f9d506b6a.htm"><span data-tocFile="../toc/IDC0JB0A.xml" class="icon toggle" onclick="ToggleExpandCollapse(this); return false;"><i class="fa fa-angle-right"> </i></span>Fields</a><ul class="toc-menu is-hidden"> </ul></li></tocItems></toc>